rediskit/__init__.py
rediskit/async_semaphore.py
rediskit/config.py
rediskit/encrypter.py
rediskit/redis_lock.py
rediskit/retry_decorator.py
rediskit/semaphore.py
rediskit/utils.py
rediskit/memoize/__init__.py
rediskit/memoize/a_memoize.py
rediskit/memoize/memoize.py
rediskit/memoize/tools.py
rediskit/redis/__init__.py
rediskit/redis/encoder.py
rediskit/redis/node.py
rediskit/redis/a_client/__init__.py
rediskit/redis/a_client/connection.py
rediskit/redis/a_client/count_op.py
rediskit/redis/a_client/hash_op.py
rediskit/redis/a_client/json_op.py
rediskit/redis/a_client/keys_op.py
rediskit/redis/a_client/pubsub.py
rediskit/redis/a_client/readiness.py
rediskit/redis/a_client/redis_in_eventloop.py
rediskit/redis/a_client/string_op.py
rediskit/redis/client/__init__.py
rediskit/redis/client/connection.py
rediskit/redis/client/count_op.py
rediskit/redis/client/hash_op.py
rediskit/redis/client/json_op.py
rediskit/redis/client/keys_op.py
rediskit/redis/client/pubsub.py
rediskit/redis/client/readiness.py
rediskit/redis/client/string_op.py
rediskit-0.0.34.dist-info/licenses/LICENSE
rediskit-0.0.34.dist-info/METADATA
rediskit-0.0.34.dist-info/WHEEL
rediskit-0.0.34.dist-info/top_level.txt
rediskit-0.0.34.dist-info/RECORD
