Metadata-Version: 2.4
Name: rediskit
Version: 0.0.34
Summary: A comprehensive Redis toolkit for Python with caching, memoization, and utilities
Author-email: Badr Elfarri <badr.elfarri@gmail.com>
Maintainer-email: Badr Elfarri <badr.elfarri@gmail.com>
License: Apache-2.0
Project-URL: Homepage, https://github.com/badrelfarri/rediskit
Project-URL: Documentation, https://github.com/badrelfarri/rediskit#readme
Project-URL: Repository, https://github.com/badrelfarri/rediskit
Project-URL: Bug Tracker, https://github.com/badrelfarri/rediskit/issues
Project-URL: Changelog, https://github.com/badrelfarri/rediskit/blob/main/CHANGELOG.md
Keywords: redis,cache,memoization,toolkit,async
Classifier: Development Status :: 3 - Alpha
Classifier: Intended Audience :: Developers
Classifier: License :: OSI Approved :: Apache Software License
Classifier: Programming Language :: Python :: 3
Requires-Python: >=3.12
License-File: LICENSE
Requires-Dist: pynacl
Requires-Dist: redis
Requires-Dist: python-redis-lock
Requires-Dist: zstd
Requires-Dist: httpx
Requires-Dist: dotenv
Dynamic: license-file
